[{"Nombre": "Gnome"}, {"Monstruo y Nivel": "Gnome, 1st-Level Warrior", "Size/Type": "Small Humanoid (Gnome)", "Hit Dice": "1d8+2 (6 hp)", "Initiative": "+0", "Speed": "20 ft. (4 squares)", "Armor Class": "16 (+1 size, +4 chain shirt, +1 light shield), touch 11, flat-footed 16", "Base Attack/Grapple": "+1/\u20133", "Attack": "Longsword +2 melee (1d6/19\u201320) or light crossbow +3 ranged (1d6/19\u201320)", "Full Attack": "Longsword +2 melee (1d6/19\u201320) or light crossbow +3 ranged (1d6/19\u201320)", "Space/Reach": "5 ft./5 ft.", "Special Attacks": "\u2014", "Special Qualities": "Gnome traits", "Saves": "Fort +4, Ref +0, Will \u20131", "Abilities": "Str 11, Dex 11, Con 14, Int 10, Wis 9, Cha 8", "Skills": "Hide +3, Listen +1, Spot +1", "Feats": "Weapon Focus (light crossbow)", "Environment": "Temperate hills (Forest gnomes: Temperate forests)", "Organization": "Company (2\u20134), squad (11\u201320 plus 1 leader of 3rd\u20136th level and 2 3rd-level lieutenants), or band (30\u201350 plus 1 3rd-level sergeant per 20 adults, 5 5th-level lieutenants, 3 7th-level captains, and 2\u20135 dire badgers)", "Challenge Rating": "1/2", "Treasure": "Standard", "Alignment": "Usually neutral good", "Advancement": "By character class", "Level Adjustment": "+0"}, {"Combate": "Gnomes prefer misdirection and deception over direct confrontation.They would rather befuddle or embarrass foes (other than goblinoids or kobolds) than kill them.Gnomes make heavy use of illusion magic and carefully prepared ambushes and traps whenever they can.Gnome Traits (Ex): Gnomes possess the following racial traits.+2 Constitution, \u20132 Strength.Small size. +1 bonus to Armor Class, +1 bonus on attack rolls, +4 bonus on Hide checks, \u20134 penalty on grapple checks, lifting and carrying limits 3/4 those of Medium characters.A gnome\u2019s base land speed is 20 feet.Low-light vision.Weapon Familiarity: Gnomes may treat gnome hooked hammers as martial weapons rather than exotic weapons.+2 racial bonus on saving throws against illusions.Add +1 to the Difficulty Class for all saving throws against illusion spells cast by gnomes. This adjustment stacks with those from similar effects, such as the Spell Focus feat.+1 racial bonus on attack rolls against kobolds and goblinoids (including goblins, hobgoblins, and bugbears).+4 dodge bonus to Armor Class against creatures of the giant type (such as ogres, troll, and hill giants).+2 racial bonus on Listen checks.+2 racial bonus on Craft (alchemy) checks.Automatic Languages: Common, Gnome. Bonus Languages: Draconic, Dwarven, Elven, Giant, Goblin, Orc.Spell-Like Abilities: 1/day\u2014speak with animals (burrowing mammal only, duration 1 minute). A gnome with a Charisma score of at least 10 also has the following spell-like abilities: 1/day\u2014dancing lights, ghost sound, prestidigitation. Caster level 1st; save DC 10 + gnome\u2019s Cha modifier + spell level.Favored Class: Bard.The gnome warrior presented here had the following ability scores before racial adjustments: Str 13, Dex 11, Con 12, Int 10, Wis 9, Cha 8."}]