[
  {
    "Nombre": "Prismatic dragon"
  },
  {
    "Monstruo y Nivel": "Sample Prismatic Dragon, Old",
    "Size/Type": "Colossal Dragon (Light)",
    "Hit Dice": "58d12+1,102 (1,479 hp hp)",
    "Initiative": "+4 (Improved Initiative)",
    "Speed": "60 ft., fly 300 ft. (clumsy)",
    "Armor Class": "78 (\u20138 size, +19 deflection, +57 natural), touch +58, flat-footed +97",
    "Base Attack/Grapple": "+58/+97",
    "Attack": "Bite +74 (4d8+23/19-20) melee",
    "Full Attack": "Bite +74 melee, 2 claws +69 (4d6+11) melee, 2 wings +68 (2d8+11) melee, tail slap +69 (4d6+34) melee",
    "Space/Reach": "30 ft./20 ft",
    "Special Attacks": "Crush 4d8+34 (DC 58), tail sweep 2d8+34 (DC 58), breath weapon, Frightful Presence (DC 58), spells (caster level 26th), spell-like abilities",
    "Special Qualities": "Immunities, DR 20/epic, SR 66, Blindsight, keen senses, deflecting force",
    "Saves": "Fort +50, Ref +31, Will +50",
    "Abilities": "Str 57, Dex 10, Con 49, Int 48, Wis 49, Cha 48",
    "Skills": "Balance +67, Bluff +80, Climb +84, Concentration +80, Diplomacy +92, Disable Device +80, Escape Artist +61, Gather Information +86, Heal +80, Intimidate +86, Jump +102, Knowledge (all) +80, Listen +80, Move Silently +61, Open Lock +61, Perform (any two) +80, Search +80, Sense Motive +80, Spellcraft +86, Spot +80, Survival +80, Tumble +67, Use Magic Device +80",
    "Feats": "Blinding Speed (\u00d72), Cleave, Flyby Attack, Great Cleave, Improved Critical (bite), Improved Initiative, Improved Sunder, Improved Spell Capacity (9th), Improved Spell Capacity (9th), Power Attack, Quicken Spell-Like Ability, Snatch, Spell Knowledge (\u00d74), Weapon Focus (bite), Weapon Focus (claw), Weapon Focus (tail slap)",
    "Environment": "Any land and underground",
    "Organization": "Solitary, pair, or family (1\u20132 and 2\u20135 off-spring)",
    "Challenge Rating": "48",
    "Treasure": "Double standard",
    "Alignment": "Usually neutral",
    "Advancement": "59\u201362 HD (Colossal)",
    "Level Adjustment": "\u2014"
  },
  {
    "Descripci\u00f3n": "A prismatic dragon\u2019s natural weapons are treated as magic (wyrmling \u2013 juvenile) or epic (young adult \u2013 great wyrm) for the purpose of overcoming damage reduction."
  },
  {
    "Combate": "Breath Weapon (Su): A prismatic dragon has one of breath weapon, a prismatic spray effect. The breath weapon\u2019s cone is of the size indicated by the dragon\u2019s size, not the normal cone for the spell.Deflecting Force (Su): A prismatic dragon is protected by a shield of shimmering light similar to a cloak of chaos that provides a deflection bonus to its AC. The deflection bonus is equal to the dragon\u2019s Charisma bonus.Immune to Light and Blindness (Ex): Prismatic dragons cannot be harmed by any light, including Evocation [Light] spells, searing light, and the various prismatic (sphere, spray, wall) spells. In addition, they are immune to any spell or effect that causes blindness.Spell-Like  At will\u2014hypnotic pattern, rainbow pattern; 3/day\u2014prismatic sphere, prismatic wall, sunbeam, sunburst. The DC is Charisma-based."
  },
  {
    "Columnas": "-----LevelAdjustment-----:-----\u2014"
  },
  {
    "Columnas": "-----Age-----Size-----HitDice(hp)-----Str-----Dex-----Con-----Int-----Wis-----Cha-----BaseAttack/-----Grapple-----Attack-----FortSave-----RefSave-----WillSave-----BreathWeapon(DC)-----FrightfulPresenceDC",
    "Fila 1": "-----Wyrmling-----H-----23d12+138(287)-----29-----10-----23-----20-----21-----20-----+23/+40-----+30-----+19-----+13-----+18-----(27)-----26",
    "Fila 2": "-----Veryyoung-----H-----28d12+196(378)-----33-----10-----25-----24-----25-----24-----+28/+47-----+37-----+23-----+16-----+23-----(31)-----31",
    "Fila 3": "-----Young-----G-----33d12+297(511)-----37-----10-----29-----28-----29-----28-----+33/+58-----+42-----+27-----+18-----+27-----(35)-----35",
    "Fila 4": "-----Juvenile-----G-----38d12+418(665)-----41-----10-----33-----32-----33-----32-----+38/+65-----+49-----+32-----+21-----+32-----(40)-----40",
    "Fila 5": "-----Youngadult-----G-----43d12+559(838)-----45-----10-----37-----36-----37-----36-----+43/+72-----+56-----+36-----+23-----+36-----(44)-----44",
    "Fila 6": "-----Adult-----C-----48d12+720(1,032)-----49-----10-----41-----40-----41-----40-----+48/+83-----+59-----+41-----+26-----+41-----(49)-----49",
    "Fila 7": "-----Matureadult-----C-----53d12+901(1,245)-----53-----10-----45-----44-----45-----44-----+53/+90-----+66-----+45-----+28-----+45-----(53)-----53",
    "Fila 8": "-----Old-----C-----58d12+1,102(1,479)-----57-----10-----49-----48-----49-----48-----+58/+97-----+73-----+50-----+31-----+50-----(58)-----58",
    "Fila 9": "-----Veryold-----C-----63d12+1,323(1,732)-----61-----10-----53-----52-----53-----52-----+63/+104-----+80-----+54-----+33-----+54-----(62)-----62",
    "Fila 10": "-----Ancient-----C+-----68d12+1,564(2,006)-----65-----10-----57-----56-----57-----56-----+68/+111-----+87-----+59-----+36-----+59-----(67)-----67",
    "Fila 11": "-----Wyrm-----C+-----73d12+1,825(2,299)-----69-----10-----61-----60-----61-----60-----+73/+118-----+94-----+63-----+38-----+63-----(71)-----71",
    "Fila 12": "-----Greatwyrm-----C+-----78d12+2,106(2,613)-----73-----10-----65-----64-----65-----64-----+78/+125-----+101-----+68-----+41-----+68-----(76)-----76"
  },
  {
    "Columnas": "-----Age-----Speed-----Initiative-----AC-----SpecialAbilities-----CasterLevel-----SR",
    "Fila 1": "-----Wyrmling-----60ft.,fly250ft.(poor)-----+0-----35(\u20132size,+5deflection,+22natural),touch13,-----flat-footed35-----Damagereduction-----10/magic,-----deflectingforce,-----hypnoticpattern-----,-----immunetolightandblindness-----5th-----24",
    "Fila 2": "-----Veryyoung-----60ft.,fly250ft.(poor)-----+0-----42(\u20132size,+7deflection,+27natural),touch15,-----flat-footed42-----8th-----30",
    "Fila 3": "-----Young-----60ft.,fly300ft.(clumsy)-----+0-----47(\u20134size,+9deflection,+32natural),touch15,-----flat-footed47-----Damagereduction-----15/magic-----11th-----36",
    "Fila 4": "-----Juvenile-----60ft.,fly300ft.(clumsy)-----+0-----54(\u20134size,+11deflection,+37natural),touch17,-----flat-footed54-----Rainbowpattern-----13th-----42",
    "Fila 5": "-----Youngadult-----60ft.,fly300ft.(clumsy)-----+0-----61(\u20134size,+13deflection,+42natural),touch19,-----flat-footed61-----Damagereduction-----15/epic-----17th-----48",
    "Fila 6": "-----Adult-----60ft.,fly300ft.(clumsy)-----+0-----64(\u20138size,+15deflection,+47natural),touch17,-----flat-footed64-----Sunbeam-----20th-----54",
    "Fila 7": "-----Matureadult-----60ft.,fly300ft.(clumsy)-----+0-----71(\u20138size,+17deflection,+52natural),touch19,-----flat-footed71-----Damagereduction-----20/epic-----23rd-----60",
    "Fila 8": "-----Old-----60ft.,fly300ft.(clumsy)-----+0-----78(\u20138size,+19deflection,+57natural),touch21,-----flat-footed78-----Sunburst-----26th-----66",
    "Fila 9": "-----Veryold-----60ft.,fly300ft.(clumsy)-----+0-----85(\u20138size,+21deflection,+62natural),touch23,-----flat-footed85-----Damagereduction-----25/epic-----29th-----68",
    "Fila 10": "-----Ancient-----60ft.,fly350ft.(clumsy)-----+0-----92(\u20138size,+23deflection,+67natural),touch25,-----flat-footed92-----Prismaticwall-----32nd-----74",
    "Fila 11": "-----Wyrm-----60ft.,fly350ft.(clumsy)-----+0-----99(\u20138size,+25deflection,+72natural),touch27,-----flat-footed99-----35th-----80",
    "Fila 12": "-----Greatwyrm-----60ft.,fly350ft.(clumsy)-----+0-----106(\u20138size,+27deflection,+77natural),touch29,-----flat-footed106-----Prismaticsphere-----38th-----86"
  }
]